lh_webtool/__init__.py
lh_webtool/crawler.py
lh_webtool/hf_download.py
lh_webtool/play_image_web.py
lh_webtool/templates/play_image.html
lh_webtool-1.3.4.dist-info/LICENSE
lh_webtool-1.3.4.dist-info/METADATA
lh_webtool-1.3.4.dist-info/WHEEL
lh_webtool-1.3.4.dist-info/entry_points.txt
lh_webtool-1.3.4.dist-info/top_level.txt
lh_webtool-1.3.4.dist-info/RECORD
