Metadata-Version: 2.1
Name: lh-webtool
Version: 1.3.4
Summary: A web tool package
Home-page: https://github.com/lh9171338/lh-webtool
Author: lh9171338
Author-email: lihao2015@whu.edu.cn
Project-URL: Bug Tracker, https://github.com/lh9171338/lh-webtool/issues
Classifier: Programming Language :: Python :: 3
Classifier: License :: OSI Approved :: MIT License
Classifier: Operating System :: OS Independent
Requires-Python: >=3.6
License-File: LICENSE
Requires-Dist: aiohttp
Requires-Dist: lxml
Requires-Dist: beautifulsoup4
Requires-Dist: Flask
Requires-Dist: lh-tool >=1.8.0
Requires-Dist: pywebio ==1.8.3
Provides-Extra: huggingface
Requires-Dist: huggingface-hub ; extra == 'huggingface'
Requires-Dist: hf-transfer ; extra == 'huggingface'
